div/__init__.py
div/div3.py
mult/__init__.py
mult/mult3.py
bibl_package2-0.1.1.dist-info/LICENSE.txt
bibl_package2-0.1.1.dist-info/METADATA
bibl_package2-0.1.1.dist-info/WHEEL
bibl_package2-0.1.1.dist-info/top_level.txt
bibl_package2-0.1.1.dist-info/RECORD
