Metadata-Version: 2.1
Name: bibl_package2
Version: 0.1.1
Summary: first py package
Author: Zilezia
Classifier: Programming Language :: Python :: 3
Classifier: License :: OSI Approved :: MIT License
Classifier: Operating System :: OS Independent
Requires-Python: >=3.6
License-File: LICENSE.txt
